{
  "id": "git-pushing",
  "name": "git-pushing",
  "summary": "Stage all changes, create a conventional commit, and push to the remote branch.",
  "description": "Stage all changes, create a conventional commit, and push to the remote branch. Use when explicitly asks to push changes (\\\"push this\\\", \\\"commit and push\\\"), mentions saving work to remote (\\\"save to github\\\", \\\"push to remote\\\"), or completes a feature and wants to share it.",
  "category": "workflow",
  "tags": [
    "workflow",
    "unknown",
    "community"
  ],
  "risk": "unknown",
  "source": "community",
  "addedAt": "2026-02-27",
  "version": "1.0.0",
  "contentPath": "skills/git-pushing/SKILL.md",
  "metadataPath": "skills/git-pushing/meta.json",
  "upstream": {
    "repo": "antigravity-awesome-skills-main",
    "path": "skills/git-pushing"
  }
}
