{
  "id": "trpc-fullstack",
  "name": "trpc-fullstack",
  "summary": "Build end-to-end type-safe APIs with tRPC — routers, procedures, middleware, subscriptions, and Next.js/React integration patterns.",
  "description": "Build end-to-end type-safe APIs with tRPC — routers, procedures, middleware, subscriptions, and Next.js/React integration patterns.",
  "category": "framework",
  "tags": [
    "typescript",
    "trpc",
    "api",
    "fullstack",
    "nextjs",
    "react",
    "type-safety",
    "framework",
    "none",
    "community"
  ],
  "risk": "none",
  "source": "community",
  "addedAt": "2026-03-17",
  "version": "1.0.0",
  "contentPath": "skills/trpc-fullstack/SKILL.md",
  "metadataPath": "skills/trpc-fullstack/meta.json",
  "upstream": {
    "repo": "antigravity-awesome-skills-main",
    "path": "skills/trpc-fullstack"
  }
}
