{
  "id": "asana-automation",
  "name": "asana-automation",
  "summary": "Automate Asana tasks via Rube MCP (Composio): tasks, projects, sections, teams, workspaces.",
  "description": "Automate Asana tasks via Rube MCP (Composio): tasks, projects, sections, teams, workspaces. Always search tools first for current schemas.",
  "category": "project-management",
  "tags": [
    "project-management",
    "unknown",
    "community"
  ],
  "risk": "unknown",
  "source": "community",
  "addedAt": "2026-02-27",
  "version": "1.0.0",
  "contentPath": "skills/asana-automation/SKILL.md",
  "metadataPath": "skills/asana-automation/meta.json",
  "upstream": {
    "repo": "antigravity-awesome-skills-main",
    "path": "skills/asana-automation"
  }
}
